Workbook

Sheet Données
A1: Tableau des charges fixes
B3: par mois | C3: par an
A4: loyer | B4: 1000 | C4: =B4*12 -> 12000
A5: cuisine | B5: =C5/12 -> 250 | C5: 3000
A6: facture edf eau | B6: 200 | C6: =B6*12 -> 2400
A7: entretien | B7: 100 | C7: =B7*12 -> 1200
A8: publicité | B8: =C8/12 -> 33.333333 | C8: 400
A9: prime assurence | B9: =C9/12 -> 100 | C9: 1200
A10: emprunt bancaire | B10: 250 | C10: =B10*12 -> 3000
A11: personnel | B11: 1365 | C11: =B11*12 -> 16380
A12: TOTAL | B12: =SUM(B4:B11) -> 3298.3333 | C12: =SUM(C4:C11) -> 39580
A15: Tableau prix de ventes
B17: prix/vente
A18: Menu 1 | B18: 15
A19: Menu 2 | B19: 25
A20: Menu 3 | B20: 35
A21: Soft | B21: 3
A22: Alcool | B22: 6
A24: Tableau des matières premiéres
B27: coût/vente
A28: Menu 1 | B28: 10
A29: Menu 2 | B29: 15
A30: Menu 3 | B30: 20
A31: Soft | B31: 1
A32: Alcool | B32: 2
A34: Taxes menu | B34: 0.05
A35: taxes boisson | B35: 0.05
A38: Tableau répartition des ventes 2016
B40: Jan | C40: Fév | D40: Mars | E40: Avr | F40: Mai | G40: Juin | H40: Juil | I40: Août | J40: Sept | K40: Oct | L40: Nov | M40: Déc | N40: TOTAL
A41: Menu 1 | B41: 130 | C41: 70 | D41: 250 | E41: 220 | F41: 70 | G41: 150 | H41: 100 | I41: 240 | J41: 60 | K41: 70 | L41: 100 | M41: 130 | N41: =SUM(B41:M41) -> 1590
A42: Menu 2 | B42: 90 | C42: 90 | D42: 210 | E42: 80 | F42: 160 | G42: 140 | H42: 200 | I42: 150 | J42: 90 | K42: 170 | L42: 230 | M42: 60 | N42: =SUM(B42:M42) -> 1670
A43: Menu 3 | B43: 80 | C43: 130 | D43: 180 | E43: 90 | F43: 210 | G43: 250 | H43: 70 | I43: 140 | J43: 80 | K43: 60 | L43: 190 | M43: 130 | N43: =SUM(B43:M43) -> 1610
A44: Soft | B44: 130 | C44: 250 | D44: 60 | E44: 190 | F44: 250 | G44: 130 | H44: 170 | I44: 110 | J44: 150 | K44: 60 | L44: 210 | M44: 60 | N44: =SUM(B44:M44) -> 1770
A45: Alcool | B45: 130 | C45: 180 | D45: 140 | E45: 240 | F45: 90 | G45: 180 | H45: 170 | I45: 90 | J45: 140 | K45: 220 | L45: 140 | M45: 190 | N45: =SUM(B45:M45) -> 1910

Sheet Bilan 2016
B1: Jan | C1: Fév | D1: Mars | E1: Avr | F1: Mai | G1: Juin | H1: Juil | I1: Août | J1: Sept | K1: Oct | L1: Nov | M1: Déc | N1: TOTAL
A2: CA menu 1 | B2: {=Données!B41:N41*Données!B18} -> 1950 | C2: 1050 | D2: 3750 | E2: 3300 | F2: 1050 | G2: 2250 | H2: 1500 | I2: 3600 | J2: 900 | K2: 1050 | L2: 1500 | M2: 1950 | N2: 23850
A3: CA menu 2 | B3: {=Données!B42:N42*Données!B19} -> 2250 | C3: 2250 | D3: 5250 | E3: 2000 | F3: 4000 | G3: 3500 | H3: 5000 | I3: 3750 | J3: 2250 | K3: 4250 | L3: 5750 | M3: 1500 | N3: 41750
A4: CA menu 3 | B4: {=Données!B43:N43*Données!B20} -> 2800 | C4: 4550 | D4: 6300 | E4: 3150 | F4: 7350 | G4: 8750 | H4: 2450 | I4: 4900 | J4: 2800 | K4: 2100 | L4: 6650 | M4: 4550 | N4: 56350
A5: CA soft | B5: {=Données!B44:N44*Données!B21} -> 390 | C5: 750 | D5: 180 | E5: 570 | F5: 750 | G5: 390 | H5: 510 | I5: 330 | J5: 450 | K5: 180 | L5: 630 | M5: 180 | N5: 5310
A6: CA alcool | B6: {=Données!B45:N45*Données!B22} -> 780 | C6: 1080 | D6: 840 | E6: 1440 | F6: 540 | G6: 1080 | H6: 1020 | I6: 540 | J6: 840 | K6: 1320 | L6: 840 | M6: 1140 | N6: 11460
A7: TOTAL CA | B7: =SUM(B2:B6) -> 8170 | C7: =SUM(C2:C6) -> 9680 | D7: =SUM(D2:D6) -> 16320 | E7: =SUM(E2:E6) -> 10460 | F7: =SUM(F2:F6) -> 13690 | G7: =SUM(G2:G6) -> 15970 | H7: =SUM(H2:H6) -> 10480 | I7: =SUM(I2:I6) -> 13120 | ... N7: =SUM(N2:N6) -> 138720
A8: Charge fixe | B8: =Données!$B$12 -> 3298.3333 | C8: =Données!$B$12 -> 3298.3333 | D8: =Données!$B$12 -> 3298.3333 | E8: =Données!$B$12 -> 3298.3333 | F8: =Données!$B$12 -> 3298.3333 | G8: =Données!$B$12 -> 3298.3333 | H8: =Données!$B$12 -> 3298.3333 | I8: =Données!$B$12 -> 3298.3333 | ... M8: =Données!$B$12 -> 3298.3333 | N8: =Données!C12 -> 39580
A9: matière 1ère menu 1 | B9: =Données!$B$28*Données!B41 -> 1300 | C9: =Données!$B$28*Données!C41 -> 700 | D9: =Données!$B$28*Données!D41 -> 2500 | E9: =Données!$B$28*Données!E41 -> 2200 | F9: =Données!$B$28*Données!F41 -> 700 | G9: =Données!$B$28*Données!G41 -> 1500 | H9: =Données!$B$28*Données!H41 -> 1000 | I9: =Données!$B$28*Données!I41 -> 2400 | ... N9: =Données!$B$28*Données!N41 -> 15900
A10: matière 1ère menu 2 | B10: =Données!$B$29*Données!B42 -> 1350 | C10: =Données!$B$29*Données!C42 -> 1350 | D10: =Données!$B$29*Données!D42 -> 3150 | E10: =Données!$B$29*Données!E42 -> 1200 | F10: =Données!$B$29*Données!F42 -> 2400 | G10: =Données!$B$29*Données!G42 -> 2100 | H10: =Données!$B$29*Données!H42 -> 3000 | I10: =Données!$B$29*Données!I42 -> 2250 | ... N10: =Données!$B$29*Données!N42 -> 25050
A11: matière 1ère menu 3 | B11: =Données!$B$30*Données!B43 -> 1600 | C11: =Données!$B$30*Données!C43 -> 2600 | D11: =Données!$B$30*Données!D43 -> 3600 | E11: =Données!$B$30*Données!E43 -> 1800 | F11: =Données!$B$30*Données!F43 -> 4200 | G11: =Données!$B$30*Données!G43 -> 5000 | H11: =Données!$B$30*Données!H43 -> 1400 | I11: =Données!$B$30*Données!I43 -> 2800 | ... N11: =Données!$B$30*Données!N43 -> 32200
A12: matière 1ère soft | B12: =Données!$B$31*Données!B44 -> 130 | C12: =Données!$B$31*Données!C44 -> 250 | D12: =Données!$B$31*Données!D44 -> 60 | E12: =Données!$B$31*Données!E44 -> 190 | F12: =Données!$B$31*Données!F44 -> 250 | G12: =Données!$B$31*Données!G44 -> 130 | H12: =Données!$B$31*Données!H44 -> 170 | I12: =Données!$B$31*Données!I44 -> 110 | ... N12: =Données!$B$31*Données!N44 -> 1770
A13: matière 1ère alcool | B13: =Données!$B$32*Données!B45 -> 260 | C13: =Données!$B$32*Données!C45 -> 360 | D13: =Données!$B$32*Données!D45 -> 280 | E13: =Données!$B$32*Données!E45 -> 480 | F13: =Données!$B$32*Données!F45 -> 180 | G13: =Données!$B$32*Données!G45 -> 360 | H13: =Données!$B$32*Données!H45 -> 340 | I13: =Données!$B$32*Données!I45 -> 180 | ... N13: =Données!$B$32*Données!N45 -> 3820
A14: taxe menu | B14: =SUM(B2:B4)*Données!$B$34 -> 350 | C14: =SUM(C2:C4)*Données!$B$34 -> 392.5 | D14: =SUM(D2:D4)*Données!$B$34 -> 765 | E14: =SUM(E2:E4)*Données!$B$34 -> 422.5 | F14: =SUM(F2:F4)*Données!$B$34 -> 620 | G14: =SUM(G2:G4)*Données!$B$34 -> 725 | H14: =SUM(H2:H4)*Données!$B$34 -> 447.5 | I14: =SUM(I2:I4)*Données!$B$34 -> 612.5 | ... N14: =SUM(N2:N4)*Données!$B$34 -> 6097.5
A15: taxe boisson | B15: =SUM(B5:B6)*Données!$B$35 -> 58.5 | C15: =SUM(C5:C6)*Données!$B$35 -> 91.5 | D15: =SUM(D5:D6)*Données!$B$35 -> 51 | E15: =SUM(E5:E6)*Données!$B$35 -> 100.5 | F15: =SUM(F5:F6)*Données!$B$35 -> 64.5 | G15: =SUM(G5:G6)*Données!$B$35 -> 73.5 | H15: =SUM(H5:H6)*Données!$B$35 -> 76.5 | I15: =SUM(I5:I6)*Données!$B$35 -> 43.5 | ... N15: =SUM(N5:N6)*Données!$B$35 -> 838.5
A16: TOTAL charges variables | B16: =SUM(B9:B15) -> 5048.5 | C16: =SUM(C9:C15) -> 5744 | D16: =SUM(D9:D15) -> 10406 | E16: =SUM(E9:E15) -> 6393 | F16: =SUM(F9:F15) -> 8414.5 | G16: =SUM(G9:G15) -> 9888.5 | H16: =SUM(H9:H15) -> 6434 | I16: =SUM(I9:I15) -> 8396 | ... N16: =SUM(N9:N15) -> 85676
A17: TOTAL des charges | B17: =B16+B8 -> 8346.8333 | C17: =C16+C8 -> 9042.3333 | D17: =D16+D8 -> 13704.333 | E17: =E16+E8 -> 9691.3333 | F17: =F16+F8 -> 11712.833 | G17: =G16+G8 -> 13186.833 | H17: =H16+H8 -> 9732.3333 | I17: =I16+I8 -> 11694.333 | ... N17: =N16+N8 -> 125256
A18: TOTAL coûts | B18: =SUM(B17) -> 8346.8333 | C18: =SUM(C17) -> 9042.3333 | D18: =SUM(D17) -> 13704.333 | E18: =SUM(E17) -> 9691.3333 | F18: =SUM(F17) -> 11712.833 | G18: =SUM(G17) -> 13186.833 | H18: =SUM(H17) -> 9732.3333 | I18: =SUM(I17) -> 11694.333 | ... N18: =SUM(N17) -> 125256
A19: Résultat | B19: =B7-B18 -> -176.83333 | C19: =C7-C18 -> 637.66667 | D19: =D7-D18 -> 2615.6667 | E19: =E7-E18 -> 768.66667 | F19: =F7-F18 -> 1977.1667 | G19: =G7-G18 -> 2783.1667 | H19: =H7-H18 -> 747.66667 | I19: =I7-I18 -> 1425.6667 | ... M19: =M7-M18 -> 315.66667 | N19: =SUM(B19:M19) -> 13464
